pyclosure/__init__.py
pyclosure/__main__.py
pyclosure/compiler.py
src/__init__.py
src/compiler.py
tests/__init__.py
tests/test_basic.py
utils/__init__.py
utils/constants.py
PyClosure-0.0.1.dist-info/LICENSE.txt
PyClosure-0.0.1.dist-info/METADATA
PyClosure-0.0.1.dist-info/WHEEL
PyClosure-0.0.1.dist-info/entry_points.txt
PyClosure-0.0.1.dist-info/top_level.txt
PyClosure-0.0.1.dist-info/RECORD
