Metadata-Version: 2.1
Name: PyClosure
Version: 0.0.1
Summary: A simple to allow to make compiling JavaScript with the Closure compiler easier.
Home-page: https://github.com/Spiderpig86/PyClosure
Author: Stanley Lim
Author-email: slim679975@gmail.com
License: MIT License
Platform: UNKNOWN
Classifier: Development Status :: 5 - Production/Stable
Classifier: Environment :: Console
Classifier: Intended Audience :: Developers
Classifier: License :: OSI Approved :: MIT License
Classifier: Natural Language :: English
Classifier: Programming Language :: Python :: 3.7
Classifier: Topic :: Software Development :: Build Tools
Requires-Python: >=3
